unieai_mcp_mysql/__init__.py
unieai_mcp_mysql/server.py
unieai_mcp_mysql/test.py
unieai_mcp_mysql-0.1.19.dist-info/licenses/LICENSE
unieai_mcp_mysql-0.1.19.dist-info/METADATA
unieai_mcp_mysql-0.1.19.dist-info/WHEEL
unieai_mcp_mysql-0.1.19.dist-info/entry_points.txt
unieai_mcp_mysql-0.1.19.dist-info/top_level.txt
unieai_mcp_mysql-0.1.19.dist-info/RECORD
