Metadata-Version: 2.4
Name: unieai_mcp_mysql
Version: 0.1.19
Summary: Internal MCP server with MySQL for UnieAI
Home-page: https://www.unieai.com/
Author: UnieAI
Author-email: contact@unieai.com
License: Proprietary
Classifier: Programming Language :: Python :: 3
Classifier: License :: Other/Proprietary License
Classifier: Operating System :: OS Independent
Requires-Python: >=3.8
License-File: LICENSE
Requires-Dist: fastmcp>=0.1.0
Requires-Dist: sqlalchemy>=2.0.0
Requires-Dist: pymysql>=1.0.2
Requires-Dist: backports.zoneinfo>=0.2.1; python_version < "3.9"
Dynamic: license-file
